homeassistant_api/__init__.py
homeassistant_api/client.py
homeassistant_api/errors.py
homeassistant_api/models/__init__.py
homeassistant_api/models/base.py
homeassistant_api/models/domains.py
homeassistant_api/models/entity.py
homeassistant_api/models/events.py
homeassistant_api/models/history.py
homeassistant_api/models/logbook.py
homeassistant_api/models/states.py
homeassistant_api/models/websocket.py
homeassistant_api/processing.py
homeassistant_api/py.typed
homeassistant_api/rawasyncclient.py
homeassistant_api/rawbaseclient.py
homeassistant_api/rawclient.py
homeassistant_api/rawwebsocket.py
homeassistant_api/utils.py
homeassistant_api/websocket.py
homeassistant_api-5.0.2.post2.dist-info/METADATA
homeassistant_api-5.0.2.post2.dist-info/WHEEL
homeassistant_api-5.0.2.post2.dist-info/licenses/LICENSE
homeassistant_api-5.0.2.post2.dist-info/RECORD
