Metadata-Version: 2.4
Name: HomeAssistant-API
Version: 5.0.2.post2
Summary: Python Wrapper for Homeassistant's REST API
License: GPL-3.0-or-later
License-File: LICENSE
Author: GrandMoff100
Author-email: minecraftcrusher100@gmail.com
Requires-Python: >=3.9,<4.0
Classifier: License :: OSI Approved :: GNU General Public License v3 or later (GPLv3+)
Classifier: Programming Language :: Python :: 3
Classifier: Programming Language :: Python :: 3.9
Classifier: Programming Language :: Python :: 3.10
Classifier: Programming Language :: Python :: 3.11
Classifier: Programming Language :: Python :: 3.12
Classifier: Programming Language :: Python :: 3.13
Classifier: Programming Language :: Python :: 3.14
Requires-Dist: aiohttp (>=3,<4)
Requires-Dist: aiohttp-client-cache (>=0,<1)
Requires-Dist: pydantic (>=2,<3)
Requires-Dist: requests (>=2,<3)
Requires-Dist: requests-cache (>=1,<2)
Requires-Dist: simplejson (>=3,<4)
Requires-Dist: websockets (>=15,<16)
Project-URL: Documentation, https://homeassistantapi.readthedocs.io
Project-URL: Homepage, https://github.com/GrandMoff100/HomeAssistantAPI
Project-URL: Repository, https://github.com/GrandMoff100/HomeAssistantAPI
